{
    "core": {
        "changeLogMessages": [
            "4.0.0.0 Preview 2 Release",
            "Add new extension packages for CloudFront Signers and EC2 Decrypt Password to take a dependency on BouncyCastle.Cryptography"
        ],
        "updateMinimum": true
    },
    "services": [
        {
            "serviceName": "DynamoDBv2",
            "type": "patch",
            "changeLogMessages": [
                "Add the ability to mock DynamoDB operations which now implement interfaces."
            ]
        },
        {
            "serviceName": "S3",
            "type": "patch",
            "changeLogMessages": [
                "Split GetACL into GetBucketAcl and GetObjectAcl",
                "Split PutACL into PutObjectACL and PutBucketACL.",
                "Obsolete PutACL and GetACL. These operations are being split into separate operations, because context parameters that could be used for endpoint resolution were not being copied over due to the two operations being merged into one. These context parameters were not being used currently so there is no effect as of now."
            ]
        }
    ],
    "overrideVersion": "4.0.0.0"
}