
{
    "simpleMethods" : {
        "operations" : {
            "ListTagsForDomain" : {
                "methodForms" : [
                    [
                        "DomainName"
                    ]
                ]
            },
            "UpdateTagsForDomain" : {
                "methodForms" : [
                    [
                        "DomainName",
                        "TagsToUpdate"
                    ]
                ]
            },
            "DeleteTagsForDomain" : {
                "methodForms" : [
                    [
                        "DomainName",
                        "TagsToDelete"
                    ]
                ]
            }
       }
    }
}